sentinel_core/__init__.py
sentinel_core/cli.py
sentinel_core/extractor.py
sentinel_core/graph_extractor.py
sentinel_core/graph_store.py
sentinel_core/models.py
sentinel_core/orchestrator.py
sentinel_core/scraper/__init__.py
sentinel_core/scraper/base.py
sentinel_core/scraper/factory.py
sentinel_core/scraper/firecrawl.py
sentinel_core/scraper/local.py
sentinel_core/scraper.py
sentinel_core-0.1.7.dist-info/entry_points.txt
sentinel_core-0.1.7.dist-info/METADATA
sentinel_core-0.1.7.dist-info/WHEEL
sentinel_core-0.1.7.dist-info/RECORD
