Metadata-Version: 2.4
Name: sentinel-core
Version: 0.1.7
Summary: Self-Healing Knowledge Graph for RAG Pipelines - pip-installable library
License: MIT
Keywords: rag,knowledge-graph,neo4j,llm,web-scraping,self-healing
Author: Om7035
Author-email: speedtech602@gmail.com
Requires-Python: >=3.11,<4.0
Classifier: Development Status :: 3 - Alpha
Classifier: Intended Audience :: Developers
Classifier: License :: OSI Approved :: MIT License
Classifier: Programming Language :: Python :: 3
Classifier: Programming Language :: Python :: 3.11
Classifier: Programming Language :: Python :: 3.12
Classifier: Programming Language :: Python :: 3.13
Classifier: Programming Language :: Python :: 3.14
Classifier: Topic :: Software Development :: Libraries :: Python Modules
Provides-Extra: all
Provides-Extra: firecrawl
Requires-Dist: beautifulsoup4 (>=4.12.0,<5.0.0)
Requires-Dist: firecrawl-py (>=0.0.5,<0.0.6) ; extra == "firecrawl" or extra == "all"
Requires-Dist: instructor (>=1.13.0,<2.0.0)
Requires-Dist: langchain-community (>=0.0.10,<0.0.11)
Requires-Dist: langchain-core (>=0.1.10,<0.2.0)
Requires-Dist: litellm (>=1.0.0,<2.0.0)
Requires-Dist: markdownify (>=0.11.0,<0.12.0)
Requires-Dist: neo4j (>=5.14.0,<6.0.0)
Requires-Dist: pydantic (>=2.5.0,<3.0.0)
Requires-Dist: python-dotenv (>=1.0.0,<2.0.0)
Requires-Dist: requests (>=2.31.0,<3.0.0)
Requires-Dist: rich (>=13.0.0,<14.0.0)
Requires-Dist: structlog (>=23.2.0,<24.0.0)
Requires-Dist: tenacity (>=8.2.3,<9.0.0)
Requires-Dist: typer (>=0.20.0,<0.21.0)
Project-URL: Documentation, https://github.com/Om7035/Sentinel-The-Self-Healing-Knowledge-Graph/docs
Project-URL: Homepage, https://github.com/Om7035/Sentinel-The-Self-Healing-Knowledge-Graph
Project-URL: Repository, https://github.com/Om7035/Sentinel-The-Self-Healing-Knowledge-Graph
